AUTHORS
LICENSE
MANIFEST.in
README.md
setup.cfg
setup.py
rapydo_utils.egg-info/PKG-INFO
rapydo_utils.egg-info/SOURCES.txt
rapydo_utils.egg-info/dependency_links.txt
rapydo_utils.egg-info/requires.txt
rapydo_utils.egg-info/top_level.txt
utilities/__init__.py
utilities/apiclient.py
utilities/basher.py
utilities/certificates.py
utilities/checks.py
utilities/cli.py
utilities/configuration.py
utilities/converter.py
utilities/cron.py
utilities/email.py
utilities/globals.py
utilities/helpers.py
utilities/htmlcodes.py
utilities/logging.ini
utilities/logging_tests.ini
utilities/logs.py
utilities/meta.py
utilities/myyaml.py
utilities/packing.py
utilities/path.py
utilities/processes.py
utilities/random.py
utilities/s3.py
utilities/template.py
utilities/time.py
utilities/uuid.py