Metadata-Version: 1.2
Name: rapydo-utils
Version: 0.6.3
Summary: A set of python utilities used across all RAPyDo projects
Home-page: https://rapydo.github.io/utils/
Author: Paolo D'Onorio De Meo
Author-email: p.donorio.de.meo@gmail.com
License: MIT
Keywords: utilities,rapydo,logs,tools
Platform: UNKNOWN
Classifier: Programming Language :: Python
Classifier: Intended Audience :: Developers
Classifier: Development Status :: 3 - Alpha
Classifier: License :: OSI Approved :: MIT License
Classifier: Programming Language :: Python :: 3.4
Classifier: Programming Language :: Python :: 3.5
Classifier: Programming Language :: Python :: 3.6
Requires-Python: >=3.4
